odoo/addons/crm_lead_api_somconnexio/CHANGELOG.md
odoo/addons/crm_lead_api_somconnexio/README.rst
odoo/addons/crm_lead_api_somconnexio/__init__.py
odoo/addons/crm_lead_api_somconnexio/__manifest__.py
odoo/addons/crm_lead_api_somconnexio/data/crm_tag.xml
odoo/addons/crm_lead_api_somconnexio/services/__init__.py
odoo/addons/crm_lead_api_somconnexio/services/crm_lead.py
odoo/addons/crm_lead_api_somconnexio/services/schemas.py
odoo/addons/crm_lead_api_somconnexio/tests/__init__.py
odoo/addons/crm_lead_api_somconnexio/tests/services/__init__.py
odoo/addons/crm_lead_api_somconnexio/tests/services/test_crm_lead.py
odoo_addon_crm_lead_api_somconnexio-16.0.1.0.2.dist-info/METADATA
odoo_addon_crm_lead_api_somconnexio-16.0.1.0.2.dist-info/WHEEL
odoo_addon_crm_lead_api_somconnexio-16.0.1.0.2.dist-info/top_level.txt
odoo_addon_crm_lead_api_somconnexio-16.0.1.0.2.dist-info/RECORD
