Metadata-Version: 2.1
Name: odoo-addon-crm-lead-api-somconnexio
Version: 16.0.1.0.2
Summary: Expose a REST API to create CRM Leads using the CRM Lead Som Connexió structure.
Home-page: https://git.coopdevs.org/coopdevs/som-connexio/odoo/odoo-somconnexio
Author: Som Connexió SCCL, Coopdevs Treball SCCL
License: AGPL-3
Platform: UNKNOWN
Classifier: Programming Language :: Python
Classifier: Framework :: Odoo
Classifier: Framework :: Odoo :: 16.0
Classifier: License :: OSI Approved :: GNU Affero General Public License v3
Requires-Python: >=3.10
Requires-Dist: odoo-addon-base-rest-somconnexio <16.1dev,>=16.0dev
Requires-Dist: odoo-addon-cooperator-somconnexio <16.1dev,>=16.0dev
Requires-Dist: odoo-addon-somconnexio <16.1dev,>=16.0dev
Requires-Dist: odoo <16.1dev,>=16.0a
